motion_master_bindings/__init__.py
motion_master_bindings/health_status.py
motion_master_bindings/motion_master_bindings.py
motion_master_bindings/network.py
motion_master_bindings-4.7.2.dist-info/METADATA
motion_master_bindings-4.7.2.dist-info/WHEEL
motion_master_bindings-4.7.2.dist-info/top_level.txt
motion_master_bindings-4.7.2.dist-info/RECORD
