Metadata-Version: 2.1
Name: motion-master-bindings
Version: 4.7.2
Summary: Python bindings for connecting to the Synapticon Motion Master
Home-page: https://www.synapticon.com
Author: Synapticon GmbH
Author-email: support@synapticon.com
Classifier: Programming Language :: Python :: 3
Classifier: Development Status :: 3 - Alpha
Classifier: Topic :: Software Development :: Libraries
Classifier: License :: OSI Approved :: MIT License
Classifier: Operating System :: OS Independent
Requires-Python: >=3.6
Requires-Dist: rx
Requires-Dist: motion-master-proto
Requires-Dist: pyzmq (<20.0)
